asterios_client/__init__.py
asterios_client/__main__.py
asterios_client/__version__.py
asterios_client-2.0.0.dist-info/METADATA
asterios_client-2.0.0.dist-info/RECORD
asterios_client-2.0.0.dist-info/WHEEL
asterios_client-2.0.0.dist-info/top_level.txt
