Metadata-Version: 2.1
Name: asterios-client
Version: 2.0.0
Summary: Asterios client
Home-page: https://github.com/maillol/asterios_client
Author: Vincent Maillol
Author-email: vincent.maillol@gmail.com
License: GPLv3
Keywords: escape game server Asterios client
Platform: UNKNOWN
Classifier: License :: OSI Approved :: GNU General Public License v3 (GPLv3)
Requires-Python: >=3.5
